triton/__init__.py
triton/_filecheck.py
triton/_internal_testing.py
triton/_utils.py
triton/errors.py
triton/knobs.py
triton/testing.py
triton/backends/__init__.py
triton/backends/compiler.py
triton/backends/driver.py
triton/compiler/__init__.py
triton/compiler/code_generator.py
triton/compiler/compiler.py
triton/compiler/errors.py
triton/compiler/make_launcher.py
triton/experimental/__init__.py
triton/experimental/gluon/__init__.py
triton/experimental/gluon/_compiler.py
triton/experimental/gluon/_runtime.py
triton/experimental/gluon/language/__init__.py
triton/experimental/gluon/language/_core.py
triton/experimental/gluon/language/_layouts.py
triton/experimental/gluon/language/_math.py
triton/experimental/gluon/language/_semantic.py
triton/experimental/gluon/language/_standard.py
triton/experimental/gluon/language/nvidia/__init__.py
triton/experimental/gluon/language/nvidia/ampere/__init__.py
triton/experimental/gluon/language/nvidia/ampere/async_copy.py
triton/experimental/gluon/language/nvidia/ampere/mbarrier.py
triton/experimental/gluon/language/nvidia/blackwell/__init__.py
triton/experimental/gluon/language/nvidia/blackwell/tma.py
triton/experimental/gluon/language/nvidia/hopper/__init__.py
triton/experimental/gluon/language/nvidia/hopper/mbarrier.py
triton/experimental/gluon/language/nvidia/hopper/tma.py
triton/experimental/gluon/nvidia/__init__.py
triton/experimental/gluon/nvidia/blackwell.py
triton/experimental/gluon/nvidia/hopper.py
triton/language/__init__.py
triton/language/core.py
triton/language/math.py
triton/language/random.py
triton/language/semantic.py
triton/language/standard.py
triton/language/extra/__init__.py
triton/language/extra/libdevice.py
triton/language/extra/cuda/__init__.py
triton/language/extra/cuda/gdc.py
triton/language/extra/cuda/language_extra.py
triton/language/extra/cuda/libdevice.py
triton/language/extra/cuda/libnvshmem_device.py
triton/language/extra/cuda/utils.py
triton/language/extra/hip/__init__.py
triton_dist-0.0.0.dist-info/METADATA
triton_dist-0.0.0.dist-info/WHEEL
triton_dist-0.0.0.dist-info/entry_points.txt
triton_dist-0.0.0.dist-info/top_level.txt
triton_dist-0.0.0.dist-info/RECORD
