Metadata-Version: 2.4
Name: triton_dist
Version: 0.0.0
Summary: Triton language and compiler extension for distributed deep learning systems
Home-page: https://github.com/ByteDance-Seed/Triton-distributed
Author: ByteDance Seed
Author-email: zheng.size@bytedance.com
Keywords: Compiler,Deep Learning,Overlapping,Distributed
Classifier: Development Status :: 4 - Beta
Classifier: Intended Audience :: Developers
Classifier: Topic :: Software Development :: Build Tools
Classifier: License :: OSI Approved :: MIT License
Classifier: Programming Language :: Python :: 3.9
Classifier: Programming Language :: Python :: 3.10
Classifier: Programming Language :: Python :: 3.11
Classifier: Programming Language :: Python :: 3.12
Classifier: Programming Language :: Python :: 3.13
Requires-Python: >=3.9,<3.14
Requires-Dist: setuptools>=40.8.0
Requires-Dist: importlib-metadata; python_version < "3.10"
Requires-Dist: packaging
Requires-Dist: cuda.core==0.2.0
Requires-Dist: cuda-python>=12.0
Requires-Dist: nvidia-nvshmem-cu12>=3.3.9
Requires-Dist: Cython>=0.29.24
Requires-Dist: nvshmem4py-cu12>=0.1.0
Provides-Extra: build
Requires-Dist: cmake<4.0,>=3.20; extra == "build"
Requires-Dist: lit; extra == "build"
Requires-Dist: ninja; extra == "build"
Requires-Dist: pybind11; extra == "build"
Provides-Extra: tests
Requires-Dist: autopep8; extra == "tests"
Requires-Dist: isort; extra == "tests"
Requires-Dist: numpy; extra == "tests"
Requires-Dist: pytest; extra == "tests"
Requires-Dist: pytest-forked; extra == "tests"
Requires-Dist: pytest-xdist; extra == "tests"
Requires-Dist: scipy>=1.7.1; extra == "tests"
Requires-Dist: llnl-hatchet; extra == "tests"
Requires-Dist: transformers; extra == "tests"
Requires-Dist: tqdm; extra == "tests"
Requires-Dist: nvidia-ml-py>=12.0; extra == "tests"
Provides-Extra: tutorials
Requires-Dist: matplotlib; extra == "tutorials"
Requires-Dist: pandas; extra == "tutorials"
Requires-Dist: tabulate; extra == "tutorials"
Requires-Dist: chardet; extra == "tutorials"
Dynamic: author
Dynamic: author-email
Dynamic: classifier
Dynamic: home-page
Dynamic: keywords
Dynamic: provides-extra
Dynamic: requires-dist
Dynamic: requires-python
Dynamic: summary
